 [
 {
    "poster": "https://raw.githubusercontent.com/Nilsn1/hindijokes/main/15.jpg"
  }, 
{
    "poster": "https://raw.githubusercontent.com/Nilsn1/hindijokes/main/14.jpg"
  }, 
{
    "poster": "https://raw.githubusercontent.com/Nilsn1/hindijokes/main/13.jpg"
  }, 
{
    "poster": "https://raw.githubusercontent.com/Nilsn1/hindijokes/main/12.jpg"
  }, 
{
    "poster": "https://raw.githubusercontent.com/Nilsn1/hindijokes/main/11.jpg"
  }, 
{
    "poster": "https://raw.githubusercontent.com/Nilsn1/hindijokes/main/10.jpg"
  }, 
{
    "poster": "https://raw.githubusercontent.com/Nilsn1/hindijokes/main/9.jpg"
  }, 
{
    "poster": "https://raw.githubusercontent.com/Nilsn1/hindijokes/main/8.jpg"
  }, 
{
    "poster": "https://raw.githubusercontent.com/Nilsn1/hindijokes/main/7.jpg"
  }, 
{
    "poster": "https://raw.githubusercontent.com/Nilsn1/hindijokes/main/6.jpg"
  }, 
{
    "poster": "https://raw.githubusercontent.com/Nilsn1/hindijokes/main/5.jpg"
  }, 
{
    "poster": "https://raw.githubusercontent.com/Nilsn1/hindijokes/main/4.jpg"
  }, 
{
    "poster": "https://raw.githubusercontent.com/Nilsn1/hindijokes/main/3.jpg"
  }, 
{
    "poster": "https://raw.githubusercontent.com/Nilsn1/hindijokes/main/2.jpg"
  }, 
{
    "poster": "https://raw.githubusercontent.com/Nilsn1/hindijokes/main/1.jpg"
  }
]
